kafka_client_decorators/__init__.py
kafka_client_decorators/decorators.py
kafka_client_decorators/client/__init__.py
kafka_client_decorators/client/client.py
kafka_client_decorators/client/consumer_builder.py
kafka_client_decorators/client/consumer_job.py
kafka_client_decorators/client/producer.py
kafka_client_decorators/client/producer_builder.py
kafka_client_decorators/kafka/__init__.py
kafka_client_decorators/kafka/client.py
kafka_client_decorators/kafka/connection_builder.py
kafka_client_decorators/kafka/connection_parameter.py
kafka_client_decorators/kafka/consumer_builder.py
kafka_client_decorators/kafka/consumer_factory.py
kafka_client_decorators/kafka/consumer_job.py
kafka_client_decorators/kafka/consumer_parameter.py
kafka_client_decorators/kafka/logging_helper.py
kafka_client_decorators/kafka/producer.py
kafka_client_decorators/kafka/producer_builder.py
kafka_client_decorators/kafka/producer_factory.py
kafka_client_decorators/kafka/producer_parameter.py
kafka_client_decorators/util/__init__.py
kafka_client_decorators/util/logging_helper.py
kafka_client_decorators-0.9.11.dist-info/LICENSE
kafka_client_decorators-0.9.11.dist-info/METADATA
kafka_client_decorators-0.9.11.dist-info/WHEEL
kafka_client_decorators-0.9.11.dist-info/top_level.txt
kafka_client_decorators-0.9.11.dist-info/RECORD
