Metadata-Version: 2.1
Name: kafka-client-decorators
Version: 0.9.11
Summary: Decorator interface to pykafka
Home-page: https://github.com/cdsedson/kafka-decorator.git
Author: Edson Cardoso
Author-email: edsonsn2@hotmail.com
License: UNKNOWN
Platform: UNKNOWN
Classifier: Programming Language :: Python :: 3
Classifier: License :: OSI Approved :: MIT License
Classifier: Operating System :: OS Independent
Requires-Python: >=3.6
Requires-Dist: pykafka (>=2.7.0)
Provides-Extra: test
Requires-Dist: mock ; extra == 'test'
Requires-Dist: nose ; extra == 'test'
Requires-Dist: coverage ; extra == 'test'
